<?xml version = '1.0' encoding = 'UTF-8'?>
<FKIndexAssociation class="oracle.dbtools.crest.model.design.relational.FKIndexAssociation" directorySegmentName="seg_0" id="80206A9F-B398-F7A5-DCFC-1CDF939301E2" containerWithKeyObject="5A1DAAC1-C16C-F518-49A0-73C7A93959CB" localFKIndex="C74F9DF0-3203-50BB-9870-2DE92DDB2694" name="IIC_IIM_FK">
<sourceConnName>aerodemo</sourceConnName>
<sourceObjSchema>AERODEMO</sourceObjSchema>
<sourceObjName>IIC_IIM_FK</sourceObjName>
<createdBy>jjs</createdBy>
<createdTime>2020-01-25 16:30:02 UTC</createdTime>
<ownerDesignName>aerodemo_sqldeveloper_model</ownerDesignName>
<importedID>7ADA2635-B498-66DD-BD7D-826072ABB4F6</importedID>
<referredTableLongName>AERODEMO.IC_ITEM_MAST</referredTableLongName>
<deleteRule>NO ACTION</deleteRule>
<referredTableID>FE5A5206-13AE-CB58-20FA-24998DA908CF</referredTableID>
<keyObject>FB140EDE-AC3E-6682-3E13-6B4A512F5BAD</keyObject>
<referredKeyID>FB140EDE-AC3E-6682-3E13-6B4A512F5BAD</referredKeyID>
<mandatory>true</mandatory>
<refColNames>ITEM_NBR</refColNames>
<transferable>true</transferable>
<rely>false</rely>
<columnDependencyConstraintGenerateInDDL>true</columnDependencyConstraintGenerateInDDL>
</FKIndexAssociation>