<?xml version = '1.0' encoding = 'UTF-8'?>
<FKIndexAssociation class="oracle.dbtools.crest.model.design.relational.FKIndexAssociation" directorySegmentName="seg_0" id="F19C1A3D-1F54-C7C7-CFCB-7D2A800D2C16" containerWithKeyObject="FE5A5206-13AE-CB58-20FA-24998DA908CF" localFKIndex="6D082DD4-CF98-CF89-D9F5-124ED39043B7" name="IIM_IIM_PRIMARY_FK">
<sourceConnName>aerodemo</sourceConnName>
<sourceObjSchema>AERODEMO</sourceObjSchema>
<sourceObjName>IIM_IIM_PRIMARY_FK</sourceObjName>
<createdBy>jjs</createdBy>
<createdTime>2020-01-25 14:09:30 UTC</createdTime>
<ownerDesignName>aerodemo_sqldeveloper_model</ownerDesignName>
<referredTableLongName>AERODEMO.IC_ITEM_MAST</referredTableLongName>
<deleteRule>NO ACTION</deleteRule>
<referredTableID>FE5A5206-13AE-CB58-20FA-24998DA908CF</referredTableID>
<keyObject>FB140EDE-AC3E-6682-3E13-6B4A512F5BAD</keyObject>
<referredKeyID>FB140EDE-AC3E-6682-3E13-6B4A512F5BAD</referredKeyID>
<mandatory>false</mandatory>
<refColNames>ITEM_NBR</refColNames>
<transferable>true</transferable>
<rely>false</rely>
<columnDependencyConstraintGenerateInDDL>true</columnDependencyConstraintGenerateInDDL>
</FKIndexAssociation>